library_management_system/__init__.py
library_management_system/admin.py
library_management_system/auth.py
library_management_system/main.py
abandon_gard_library_management_sytm-1.0.0.dist-info/METADATA
abandon_gard_library_management_sytm-1.0.0.dist-info/WHEEL
abandon_gard_library_management_sytm-1.0.0.dist-info/entry_points.txt
abandon_gard_library_management_sytm-1.0.0.dist-info/top_level.txt
abandon_gard_library_management_sytm-1.0.0.dist-info/RECORD
