Metadata-Version: 2.1
Name: abandon-gard-library-management-sytm
Version: 1.0.0
Summary: A library management system with user registration, login, and admin functions.
Home-page: UNKNOWN
Author: Your Name
Author-email: your_email@example.com
License: UNKNOWN
Platform: UNKNOWN
